odoo/addons/hr_employee_second_lastname/README.rst
odoo/addons/hr_employee_second_lastname/__init__.py
odoo/addons/hr_employee_second_lastname/__manifest__.py
odoo/addons/hr_employee_second_lastname/hooks.py
odoo/addons/hr_employee_second_lastname/i18n/ca.po
odoo/addons/hr_employee_second_lastname/i18n/es.po
odoo/addons/hr_employee_second_lastname/i18n/fr.po
odoo/addons/hr_employee_second_lastname/i18n/hr.po
odoo/addons/hr_employee_second_lastname/i18n/hr_employee_lastnames.pot
odoo/addons/hr_employee_second_lastname/i18n/hr_employee_second_lastname.pot
odoo/addons/hr_employee_second_lastname/i18n/it.po
odoo/addons/hr_employee_second_lastname/i18n/pt_BR.po
odoo/addons/hr_employee_second_lastname/models/__init__.py
odoo/addons/hr_employee_second_lastname/models/hr_employee.py
odoo/addons/hr_employee_second_lastname/models/hr_employee_base.py
odoo/addons/hr_employee_second_lastname/readme/CONTRIBUTORS.md
odoo/addons/hr_employee_second_lastname/readme/DESCRIPTION.md
odoo/addons/hr_employee_second_lastname/readme/USAGE.md
odoo/addons/hr_employee_second_lastname/static/description/icon.png
odoo/addons/hr_employee_second_lastname/static/description/index.html
odoo/addons/hr_employee_second_lastname/tests/__init__.py
odoo/addons/hr_employee_second_lastname/tests/test_hr_employee_second_lastname.py
odoo/addons/hr_employee_second_lastname/views/hr_views.xml
odoo_addon_hr_employee_second_lastname-18.0.1.0.0.5.dist-info/METADATA
odoo_addon_hr_employee_second_lastname-18.0.1.0.0.5.dist-info/WHEEL
odoo_addon_hr_employee_second_lastname-18.0.1.0.0.5.dist-info/top_level.txt
odoo_addon_hr_employee_second_lastname-18.0.1.0.0.5.dist-info/RECORD
